cutsets.py
cutsets-1.2.dist-info/LICENSE
cutsets-1.2.dist-info/METADATA
cutsets-1.2.dist-info/WHEEL
cutsets-1.2.dist-info/top_level.txt
cutsets-1.2.dist-info/RECORD
