Metadata-Version: 2.1
Name: cutsets
Version: 1.2
Summary: Computation of minimal cutsets using MOCUS Algorithm
Home-page: https://github.com/iamumairs/fault-tree-mcs
Author: Umair Siddique
License: MIT
Platform: UNKNOWN
Classifier: Programming Language :: Python :: 3
Classifier: License :: OSI Approved :: MIT License
Classifier: Operating System :: OS Independent
Requires-Python: >=3.6
Requires-Dist: pandas
